django_prompt_responses-0.1.1.dist-info/DESCRIPTION.rst
django_prompt_responses-0.1.1.dist-info/METADATA
django_prompt_responses-0.1.1.dist-info/RECORD
django_prompt_responses-0.1.1.dist-info/WHEEL
django_prompt_responses-0.1.1.dist-info/metadata.json
django_prompt_responses-0.1.1.dist-info/top_level.txt
prompt_responses/__init__.py
prompt_responses/admin.py
prompt_responses/apps.py
prompt_responses/forms.py
prompt_responses/models.py
prompt_responses/serializers.py
prompt_responses/urls.py
prompt_responses/views.py
prompt_responses/viewsets.py
prompt_responses/migrations/0001_initial.py
prompt_responses/migrations/0002_auto_20171113_0216.py
prompt_responses/migrations/0003_auto_20171113_0217.py
prompt_responses/migrations/0004_auto_20171113_0234.py
prompt_responses/migrations/0005_auto_20171129_0534.py
prompt_responses/migrations/0006_prompt_name.py
prompt_responses/migrations/__init__.py
