Metadata-Version: 2.0
Name: django-prompt-responses
Version: 0.1.1
Summary: A flexible prompt and user responses data schema utilizing the generic content types
Home-page: https://github.com/graup/django-prompt-responses
Author: Paul Grau
Author-email: paul@graycoding.com
License: MIT
Keywords: django-prompt-responses
Platform: UNKNOWN
Classifier: Development Status :: 3 - Alpha
Classifier: Framework :: Django
Classifier: Framework :: Django :: 1.8
Classifier: Framework :: Django :: 1.9
Classifier: Framework :: Django :: 1.10
Classifier: Intended Audience :: Developers
Classifier: License :: OSI Approved :: BSD License
Classifier: Natural Language :: English
Classifier: Programming Language :: Python :: 2
Classifier: Programming Language :: Python :: 2.7
Classifier: Programming Language :: Python :: 3
Classifier: Programming Language :: Python :: 3.3
Classifier: Programming Language :: Python :: 3.4
Classifier: Programming Language :: Python :: 3.5
Requires-Dist: django-model-utils (>=2.0)
Requires-Dist: django-sortedm2m (>=1.5)
